<?xml version="1.0" encoding="UTF-8"?><Korisnici xmlns="http://www.ftn.uns.ac.rs/korisnici">
    <Korisnik>
        <KorisnickoIme>sf</KorisnickoIme>
        <Lozinka>UTRm/goKSNXzcm95MV/4IFmoZqPvXCrsH2ULF7HDgT8=$R3qDKUU3Ceb3Kw+Aew0YfZ9+ytrXYU8fHEUL+Ry9fW0=</Lozinka>
        <Ime>asa</Ime>
        <Prezime>asax</Prezime>
        <Uloga>gradjanin</Uloga>
        <Email><xenc:EncryptedData xmlns:xenc="http://www.w3.org/2001/04/xmlenc#" Type="http://www.w3.org/2001/04/xmlenc#Content"><xenc:EncryptionMethod Algorithm="http://www.w3.org/2001/04/xmlenc#tripledes-cbc"/><xenc:CipherData><xenc:CipherValue>RLE5aqI9AI9u3e5sr1lfvQ==</xenc:CipherValue></xenc:CipherData></xenc:EncryptedData></Email>
        <TimeStamp>Thu Jun 16 04:28:08 CEST 2016</TimeStamp>
    </Korisnik>
    <Korisnik>
        <KorisnickoIme>milos</KorisnickoIme>
        <Lozinka>2C/V8kSRP+ZO78x3+xjWZYH2FkbhAQEeSfYp6xIZOTA=$TJpyfizL7MAGFlIbrUnAJxRJsoUrwxcZ5S5bOAKJRRs=</Lozinka>
        <Ime>milos</Ime>
        <Prezime>savic</Prezime>
        <Uloga>gradjanin</Uloga>
        <Email><xenc:EncryptedData xmlns:xenc="http://www.w3.org/2001/04/xmlenc#" Type="http://www.w3.org/2001/04/xmlenc#Content"><xenc:EncryptionMethod Algorithm="http://www.w3.org/2001/04/xmlenc#tripledes-cbc"/><xenc:CipherData><xenc:CipherValue>RNlwOc+kcTWZe0IpuS2qAw==</xenc:CipherValue></xenc:CipherData></xenc:EncryptedData></Email>
        <TimeStamp>Thu Jun 16 04:32:36 CEST 2016</TimeStamp>
    </Korisnik>
    <Korisnik>
        <KorisnickoIme>milos321</KorisnickoIme>
        <Lozinka>Wf1mIYtgEEH3fiqzM2mq7C84I9hWOxtYxgdKzFODe60=$m04BAnvdf8Qh1BU/HTS0e0/ZVhTo75rRn3RtCm8YK/k=</Lozinka>
        <Ime>milos</Ime>
        <Prezime>savic</Prezime>
        <Uloga>gradjanin</Uloga>
        <Email><xenc:EncryptedData xmlns:xenc="http://www.w3.org/2001/04/xmlenc#" Type="http://www.w3.org/2001/04/xmlenc#Content"><xenc:EncryptionMethod Algorithm="http://www.w3.org/2001/04/xmlenc#tripledes-cbc"/><xenc:CipherData><xenc:CipherValue>/8fvtoA1b78YrIqbp8lndg==</xenc:CipherValue></xenc:CipherData></xenc:EncryptedData></Email>
        <TimeStamp>Thu Jun 16 04:37:11 CEST 2016</TimeStamp>
    </Korisnik>
    <Korisnik>
        <KorisnickoIme>a</KorisnickoIme>
        <Lozinka>jNpqNXoENsjW4u0bCSE2pjelIWsMcsCUYCRNDVIncqE=$ionNxG7oex7fu1xciLRVWYmJQYvvGM6wDI+wcD7ZYxM=</Lozinka>
        <Ime>sad</Ime>
        <Prezime>asdad</Prezime>
        <Uloga>gradjanin</Uloga>
        <Email><xenc:EncryptedData xmlns:xenc="http://www.w3.org/2001/04/xmlenc#" Type="http://www.w3.org/2001/04/xmlenc#Content"><xenc:EncryptionMethod Algorithm="http://www.w3.org/2001/04/xmlenc#tripledes-cbc"/><xenc:CipherData><xenc:CipherValue>FMqilmpLzjGZoFWM1uif1g==</xenc:CipherValue></xenc:CipherData></xenc:EncryptedData></Email>
        <TimeStamp>Thu Jun 16 04:48:38 CEST 2016</TimeStamp>
    </Korisnik>
    <Korisnik>
        <KorisnickoIme>rale</KorisnickoIme>
        <Lozinka>E3ol4VG6XgAWwA2UJfig5YpXw3J9HKwWTFGdcRl+nsY=$uAYibDw6sxQZCwoj8Y0q544cRimjvYqRz+knD3MlwS0=</Lozinka>
        <Ime>rale</Ime>
        <Prezime>sa</Prezime>
        <Uloga>gradjanin</Uloga>
        <Email><xenc:EncryptedData xmlns:xenc="http://www.w3.org/2001/04/xmlenc#" Type="http://www.w3.org/2001/04/xmlenc#Content"><xenc:EncryptionMethod Algorithm="http://www.w3.org/2001/04/xmlenc#tripledes-cbc"/><xenc:CipherData><xenc:CipherValue>FJ50XEv98MS8IB4Pur3vcQ==</xenc:CipherValue></xenc:CipherData></xenc:EncryptedData></Email>
        <TimeStamp>Thu Jun 16 14:52:01 CEST 2016</TimeStamp>
    </Korisnik>
    <Korisnik>
        <KorisnickoIme>rale</KorisnickoIme>
        <Lozinka>Bu2KyrjKRVezf8ovX1SK6Pv6G1C0XUrjSLhudD6tnxg=$66/bo2/ovUWO8HYovnHNumauaRY1KfCTEgknFT/m/58=</Lozinka>
        <Ime>rale</Ime>
        <Prezime>sa</Prezime>
        <Uloga>gradjanin</Uloga>
        <Email><xenc:EncryptedData xmlns:xenc="http://www.w3.org/2001/04/xmlenc#" Type="http://www.w3.org/2001/04/xmlenc#Content"><xenc:EncryptionMethod Algorithm="http://www.w3.org/2001/04/xmlenc#tripledes-cbc"/><xenc:CipherData><xenc:CipherValue>CM2cmOdAnKLRvOwVCy4YiA==</xenc:CipherValue></xenc:CipherData></xenc:EncryptedData></Email>
        <TimeStamp>Thu Jun 16 14:57:33 CEST 2016</TimeStamp>
    </Korisnik>
    <Korisnik>
        <KorisnickoIme>d</KorisnickoIme>
        <Lozinka>skNHzYAyaEIaosLckTKCGN9qhZo2Tme+PEUXw3KqY0E=$rGRL+9WXlK2bdt1jUgvO85a4sAKqHIORZI64HH6UR0U=</Lozinka>
        <Ime>d</Ime>
        <Prezime>d</Prezime>
        <Uloga>gradjanin</Uloga>
        <Email><xenc:EncryptedData xmlns:xenc="http://www.w3.org/2001/04/xmlenc#" Type="http://www.w3.org/2001/04/xmlenc#Content"><xenc:EncryptionMethod Algorithm="http://www.w3.org/2001/04/xmlenc#tripledes-cbc"/><xenc:CipherData><xenc:CipherValue>Sar2BQVqfLp1hK8bIg3VDg==</xenc:CipherValue></xenc:CipherData></xenc:EncryptedData></Email>
        <TimeStamp>Thu Jun 16 14:57:46 CEST 2016</TimeStamp>
    </Korisnik>
    <Korisnik>
        <KorisnickoIme>aa</KorisnickoIme>
        <Lozinka>q6tOEjWWgKY8veKfXcrxjKUZZc+2eyNlsO3gTM7XUxs=$HEPggnujskpVkCcLJ69yJM+6e01Kb3ZALg4NtqvatsA=</Lozinka>
        <Ime>aa</Ime>
        <Prezime>aa</Prezime>
        <Uloga>gradjanin</Uloga>
        <Email><xenc:EncryptedData xmlns:xenc="http://www.w3.org/2001/04/xmlenc#" Type="http://www.w3.org/2001/04/xmlenc#Content"><xenc:EncryptionMethod Algorithm="http://www.w3.org/2001/04/xmlenc#tripledes-cbc"/><xenc:CipherData><xenc:CipherValue>EXtoH2AjJgfwTKQ1bIYElQ==</xenc:CipherValue></xenc:CipherData></xenc:EncryptedData></Email>
        <TimeStamp>Thu Jun 16 15:04:27 CEST 2016</TimeStamp>
    </Korisnik>
    <Korisnik>
        <KorisnickoIme>z</KorisnickoIme>
        <Lozinka>Au7N+Uv+O0m8KCXZShXnAwHHw5v3LOF/Vxd83CngBms=$nBI9MRnPupbEd51XYILUVbhVLWqIrB7N8IIPmF1jXPU=</Lozinka>
        <Ime>z</Ime>
        <Prezime>z</Prezime>
        <Uloga>gradjanin</Uloga>
        <Email><xenc:EncryptedData xmlns:xenc="http://www.w3.org/2001/04/xmlenc#" Type="http://www.w3.org/2001/04/xmlenc#Content"><xenc:EncryptionMethod Algorithm="http://www.w3.org/2001/04/xmlenc#tripledes-cbc"/><xenc:CipherData><xenc:CipherValue>FgZAiJN0NEO+PTzysc7O2g==</xenc:CipherValue></xenc:CipherData></xenc:EncryptedData></Email>
        <TimeStamp>Thu Jun 16 15:09:35 CEST 2016</TimeStamp>
    </Korisnik>
    <Korisnik>
        <KorisnickoIme>r</KorisnickoIme>
        <Lozinka>rho7bMW7851wjDukpoyJ0ExcxA62ZWLh/ROLsIo0x1g=$14znUzi9szOlLAq6qrueXBadioZY04KPLGYWLZrrALc=</Lozinka>
        <Ime>r</Ime>
        <Prezime>r</Prezime>
        <Uloga>gradjanin</Uloga>
        <Email><xenc:EncryptedData xmlns:xenc="http://www.w3.org/2001/04/xmlenc#" Type="http://www.w3.org/2001/04/xmlenc#Content"><xenc:EncryptionMethod Algorithm="http://www.w3.org/2001/04/xmlenc#tripledes-cbc"/><xenc:CipherData><xenc:CipherValue>5aPXo9Gv9DzanupDH4jGfg==</xenc:CipherValue></xenc:CipherData></xenc:EncryptedData></Email>
        <TimeStamp>Thu Jun 16 15:19:35 CEST 2016</TimeStamp>
    </Korisnik>
    <Korisnik>
        <KorisnickoIme>ff</KorisnickoIme>
        <Lozinka>hOXqjTHT+WqsqKlsHA8Hb53YZQdwDFHtxQdQQsu5FI4=$MWVO445NqN03dN6bONdC9kGnZzNZKYXfrska9YInn7U=</Lozinka>
        <Ime>sa</Ime>
        <Prezime>sa</Prezime>
        <Uloga>gradjanin</Uloga>
        <Email><xenc:EncryptedData xmlns:xenc="http://www.w3.org/2001/04/xmlenc#" Type="http://www.w3.org/2001/04/xmlenc#Content"><xenc:EncryptionMethod Algorithm="http://www.w3.org/2001/04/xmlenc#tripledes-cbc"/><xenc:CipherData><xenc:CipherValue>T1RFrGfqMlPGKYeoxppikg==</xenc:CipherValue></xenc:CipherData></xenc:EncryptedData></Email>
        <TimeStamp>Thu Jun 16 15:29:49 CEST 2016</TimeStamp>
    </Korisnik>
    <Korisnik>
        <KorisnickoIme>gg</KorisnickoIme>
        <Lozinka>zaj+OLpTbW0uDo/doWept/R5DSnG/rfnqlM22Rp/xqA=$EOYP53yJhU58LdHMXO/5+YkUWEb6CVrhBbqDlBjtGdk=</Lozinka>
        <Ime>gg</Ime>
        <Prezime>gg</Prezime>
        <Uloga>gradjanin</Uloga>
        <Email><xenc:EncryptedData xmlns:xenc="http://www.w3.org/2001/04/xmlenc#" Type="http://www.w3.org/2001/04/xmlenc#Content"><xenc:EncryptionMethod Algorithm="http://www.w3.org/2001/04/xmlenc#tripledes-cbc"/><xenc:CipherData><xenc:CipherValue>QI/q1F02SX24r7SCGmQFSw==</xenc:CipherValue></xenc:CipherData></xenc:EncryptedData></Email>
        <TimeStamp>Thu Jun 16 15:31:41 CEST 2016</TimeStamp>
    </Korisnik>
    <Korisnik>
        <KorisnickoIme>uu</KorisnickoIme>
        <Lozinka>6hWOp5NXRNETWEjEmDjc29kxbaVxL+WNhYTZNhTfAJU=$vsN8tQoPXVh96h528uMoEYjHYz83yq0xQ34IeaGxkGM=</Lozinka>
        <Ime>uu</Ime>
        <Prezime>uu</Prezime>
        <Uloga>gradjanin</Uloga>
        <Email><xenc:EncryptedData xmlns:xenc="http://www.w3.org/2001/04/xmlenc#" Type="http://www.w3.org/2001/04/xmlenc#Content"><xenc:EncryptionMethod Algorithm="http://www.w3.org/2001/04/xmlenc#tripledes-cbc"/><ds:KeyInfo xmlns:ds="http://www.w3.org/2000/09/xmldsig#">
<ds:KeyName>Kriptovani tajni kljuc</ds:KeyName>
<xenc:EncryptedKey><xenc:EncryptionMethod Algorithm="http://www.w3.org/2001/04/xmlenc#rsa-1_5"/><xenc:CipherData><xenc:CipherValue>fWMY/Xblcg0uz8+H4mDbTvozH3UUl6IzmJ105qqDl/TcEI/Fh7h7yai2soVFLu2lWdxwLKmBQaXV
hZBLqyGZ/+ay3VcKyPBoxYQeUdgjZuJCBJDAsHgN4kAJZ8pBB+1XE0Mb/uhd3Z86bso15Nl0SA30
0sf36mcR6zYMM8xoKs0=</xenc:CipherValue></xenc:CipherData></xenc:EncryptedKey></ds:KeyInfo><xenc:CipherData><xenc:CipherValue>K04pY5pzA8sIytrg9HaH/w==</xenc:CipherValue></xenc:CipherData></xenc:EncryptedData></Email>
        <TimeStamp>Thu Jun 16 15:34:56 CEST 2016</TimeStamp>
    </Korisnik>
</Korisnici>